formaloo/__init__.py
formaloo/client.py
formaloo/constants.py
formaloo/helper.py
formaloo/settings.py
formaloo/tags.py
formaloo/activities/__init__.py
formaloo/activities/activity.py
formaloo/activities/batch.py
formaloo/customers/__init__.py
formaloo/customers/batch.py
formaloo/customers/customer.py
formaloo/forms/__init__.py
formaloo/forms/category.py
formaloo/forms/field.py
formaloo/forms/form.py
formaloo/forms/form_display.py
formaloo/forms/payment_method.py
formaloo/forms/row_tag.py
formaloo/forms/row_vote.py
formaloo/forms/template.py
formaloo/gamification/__init__.py
formaloo/gamification/job.py
tests/__init__.py
formaloo_cdp-0.4.0.dist-info/LICENSE
formaloo_cdp-0.4.0.dist-info/METADATA
formaloo_cdp-0.4.0.dist-info/WHEEL
formaloo_cdp-0.4.0.dist-info/top_level.txt
formaloo_cdp-0.4.0.dist-info/RECORD
