Metadata-Version: 2.1
Name: formaloo-cdp
Version: 0.4.0
Summary: Official SDK to use Formaloo API
Home-page: https://github.com/formaloo/formaloo-python
Author: Formaloo
Author-email: info@formaloo.com
License: UNKNOWN
Project-URL: Bug Tracker, https://github.com/formaloo/formaloo-python/issues
Platform: UNKNOWN
Classifier: Programming Language :: Python :: 3
Classifier: License :: OSI Approved :: MIT License
Classifier: Operating System :: OS Independent
Requires-Python: >=3.6
License-File: LICENSE
Requires-Dist: environs (==9.*)
Requires-Dist: requests (==2.*)
